polimer_solibity_calculator/__init__.py
polimer_solibity_calculator/__main__.py
polimer_solibity_calculator/cli_parser.py
polimer_solibity_calculator/data.json
polimer_solibity_calculator/entry.py
polimer_solibity_calculator/main.py
polimer_solibity_calculator/version.py
polimer_solibity_calculator/scripts/entry.bat
polimer_solibity_calculator/scripts/instalation.bat
polimer_solibity_calculator/scripts/main.bat
pcs_3d-1.4.1.dist-info/LICENSE
pcs_3d-1.4.1.dist-info/METADATA
pcs_3d-1.4.1.dist-info/WHEEL
pcs_3d-1.4.1.dist-info/top_level.txt
pcs_3d-1.4.1.dist-info/RECORD
