Metadata-Version: 2.1
Name: pcs-3d
Version: 1.4.1
Summary: # Solubility Calculator (Version: 1.4.1)
Home-page: UNKNOWN
Author: Ronald Oguz
Author-email: 
License: UNKNOWN
Platform: UNKNOWN
License-File: LICENSE
